README.txt
setup.py
pyf/__init__.py
pyf.warehouse.egg-info/PKG-INFO
pyf.warehouse.egg-info/SOURCES.txt
pyf.warehouse.egg-info/dependency_links.txt
pyf.warehouse.egg-info/entry_points.txt
pyf.warehouse.egg-info/namespace_packages.txt
pyf.warehouse.egg-info/not-zip-safe
pyf.warehouse.egg-info/requires.txt
pyf.warehouse.egg-info/top_level.txt
pyf/warehouse/__init__.py
pyf/warehouse/storage.py