Metadata-Version: 1.0
Name: pyf.warehouse
Version: 1.0
Summary: High-level dataflow storage system for PyF framework
Home-page: http://svn.plone.org/svn/collective/
Author: UNKNOWN
Author-email: UNKNOWN
License: MIT
Platform: UNKNOWN
Classifier: Programming Language :: Python
